killeengeo/__init__.py
killeengeo/core.py
killeengeo/exceptions.py
killeengeo/hyperplane.py
killeengeo/random.py
killeengeo/ray.py
killeengeo/segment.py
killeengeo/typing.py
killeengeo/utils.py
killeengeo-0.0.5.dist-info/LICENSE
killeengeo-0.0.5.dist-info/METADATA
killeengeo-0.0.5.dist-info/WHEEL
killeengeo-0.0.5.dist-info/top_level.txt
killeengeo-0.0.5.dist-info/RECORD
