Metadata-Version: 2.1
Name: killeengeo
Version: 0.0.5
Summary: 2D and 3D geometry in Python.
Home-page: https://killeengeo.readthedocs.io/en/latest/
Author: Benjamin D. Killeen
Author-email: killeen@jhu.edu
Requires-Python: >=3.10
License-File: LICENSE
Requires-Dist: numpy
Requires-Dist: scipy
Requires-Dist: typing-extensions
